fload_freedb/__init__.py
fload_freedb/freedb.py
fload_freedb/stream/__init__.py
fload_freedb/stream/base.py
fload_freedb/stream/freedbdelete.py
fload_freedb/stream/freedbdoc.py
fload_freedb/stream/freedbfilter.py
fload_freedb/stream/fromfreedb.py
fload_freedb/stream/tofreedb.py
fload_freedb-0.0.5.dist-info/LICENSE
fload_freedb-0.0.5.dist-info/METADATA
fload_freedb-0.0.5.dist-info/WHEEL
fload_freedb-0.0.5.dist-info/entry_points.txt
fload_freedb-0.0.5.dist-info/top_level.txt
fload_freedb-0.0.5.dist-info/RECORD
