Metadata-Version: 2.1
Name: fload-freedb
Version: 0.0.5
Summary: A fload plugin work together with freedb
Home-page: http://github.com/kevenli/fload-freedb
Author: Keven Li
Author-email: pbleester@gmail.com
License: UNKNOWN
Platform: UNKNOWN
Requires-Dist: requests
